groqon/__init__.py
groqon/app.py
groqon/async_api/__init__.py
groqon/async_api/agroq_client.py
groqon/async_api/agroq_server.py
groqon/async_api/agroq_utils.py
groqon/async_api/schema.py
groqon/cli.py
groqon/element_selectors.py
groqon/groq_config.py
groqon/logger.py
groqon/utils.py
groqon-0.2.0.dist-info/METADATA
groqon-0.2.0.dist-info/WHEEL
groqon-0.2.0.dist-info/entry_points.txt
groqon-0.2.0.dist-info/RECORD
