Metadata-Version: 2.1
Name: groqon
Version: 0.2.0
Summary: Use Groq.com as llm
Author: tikendraw
Author-email: tikendraksahu1029@gmail.com
Requires-Python: >=3.11,<4.0
Classifier: Programming Language :: Python :: 3
Classifier: Programming Language :: Python :: 3.11
Classifier: Programming Language :: Python :: 3.12
Requires-Dist: aiofiles (>=23.2.1,<24.0.0)
Requires-Dist: click (>=8.1.7,<9.0.0)
Requires-Dist: fastapi (>=0.111.0,<0.112.0)
Requires-Dist: icecream (>=2.1.3,<3.0.0)
Requires-Dist: line-profiler (>=4.1.3,<5.0.0)
Requires-Dist: playwright (==1.44.0)
Requires-Dist: termcolor (>=2.4.0,<3.0.0)
Requires-Dist: uvicorn (>=0.30.1,<0.31.0)
